[
	{
		"key": "dbln",
		"value": "%7B%2261571867821788%22%3A%226NnbCvWV%22%2C%22100071295286104%22%3A%22GX1UaJ9y%22%7D",
		"domain": "facebook.com",
		"path": "/login/device-based/",
		"hostOnly": false,
		"creation": "2025-02-27T05:03:44.695Z",
		"lastAccessed": "2025-02-27T05:03:44.695Z"
	},
	{
		"key": "datr",
		"value": "vuJYZ80Y4nOf4z5ZHIRe7ZGf",
		"domain": "facebook.com",
		"path": "/",
		"hostOnly": false,
		"creation": "2025-02-27T05:03:44.695Z",
		"lastAccessed": "2025-02-27T05:03:44.695Z"
	},
	{
		"key": "sb",
		"value": "vuJYZ3_yMmDZQL4BjBe9k2Ay",
		"domain": "facebook.com",
		"path": "/",
		"hostOnly": false,
		"creation": "2025-02-27T05:03:44.695Z",
		"lastAccessed": "2025-02-27T05:03:44.695Z"
	},
	{
		"key": "ps_l",
		"value": "1",
		"domain": "facebook.com",
		"path": "/",
		"hostOnly": false,
		"creation": "2025-02-27T05:03:44.695Z",
		"lastAccessed": "2025-02-27T05:03:44.695Z"
	},
	{
		"key": "ps_n",
		"value": "1",
		"domain": "facebook.com",
		"path": "/",
		"hostOnly": false,
		"creation": "2025-02-27T05:03:44.695Z",
		"lastAccessed": "2025-02-27T05:03:44.695Z"
	},
	{
		"key": "ar_debug",
		"value": "1",
		"domain": "facebook.com",
		"path": "/",
		"hostOnly": false,
		"creation": "2025-02-27T05:03:44.695Z",
		"lastAccessed": "2025-02-27T05:03:44.695Z"
	},
	{
		"key": "wl_cbv",
		"value": "v2%3Bclient_version%3A2701%3Btimestamp%3A1735568985",
		"domain": "facebook.com",
		"path": "/",
		"hostOnly": false,
		"creation": "2025-02-27T05:03:44.695Z",
		"lastAccessed": "2025-02-27T05:03:44.695Z"
	},
	{
		"key": "dpr",
		"value": "1.25",
		"domain": "facebook.com",
		"path": "/",
		"hostOnly": false,
		"creation": "2025-02-27T05:03:44.695Z",
		"lastAccessed": "2025-02-27T05:03:44.695Z"
	},
	{
		"key": "usida",
		"value": "eyJ2ZXIiOjEsImlkIjoiQXNxc3hoNDMxdTkzZyIsInRpbWUiOjE3MzgwNzI2OTh9",
		"domain": "facebook.com",
		"path": "/",
		"hostOnly": false,
		"creation": "2025-02-27T05:03:44.695Z",
		"lastAccessed": "2025-02-27T05:03:44.695Z"
	},
	{
		"key": "wd",
		"value": "1536x730",
		"domain": "facebook.com",
		"path": "/",
		"hostOnly": false,
		"creation": "2025-02-27T05:03:44.695Z",
		"lastAccessed": "2025-02-27T05:03:44.695Z"
	},
	{
		"key": "locale",
		"value": "vi_VN",
		"domain": "facebook.com",
		"path": "/",
		"hostOnly": false,
		"creation": "2025-02-27T05:03:44.695Z",
		"lastAccessed": "2025-02-27T05:03:44.695Z"
	},
	{
		"key": "c_user",
		"value": "100071295286104",
		"domain": "facebook.com",
		"path": "/",
		"hostOnly": false,
		"creation": "2025-02-27T05:03:44.695Z",
		"lastAccessed": "2025-02-27T05:03:44.695Z"
	},
	{
		"key": "xs",
		"value": "10%3AwxZv0jkIDY9vAw%3A2%3A1740632618%3A-1%3A6279",
		"domain": "facebook.com",
		"path": "/",
		"hostOnly": false,
		"creation": "2025-02-27T05:03:44.695Z",
		"lastAccessed": "2025-02-27T05:03:44.695Z"
	},
	{
		"key": "fr",
		"value": "1SF6pzmCs2579V8Hn.AWWf4ahIbNkg7sXBK4foZl1hGUQ-2VdZzY0zew.Bnv_Hy..AAA.0.0.Bnv_Is.AWVl-6b53PI",
		"domain": "facebook.com",
		"path": "/",
		"hostOnly": false,
		"creation": "2025-02-27T05:03:44.695Z",
		"lastAccessed": "2025-02-27T05:03:44.695Z"
	}
]
